anytls/__init__.py
anytls/logging_config.py
anytls/main.py
anytls/py.typed
anytls/cli/__init__.py
anytls/cli/check.py
anytls/cli/install.py
anytls/cli/log.py
anytls/cli/remove.py
anytls/cli/self_.py
anytls/cli/start.py
anytls/cli/stop.py
anytls/cli/update.py
anytls/core/__init__.py
anytls/core/constants.py
anytls/core/manager.py
anytls/core/utils.py
anytls_py-0.1.14.dist-info/METADATA
anytls_py-0.1.14.dist-info/WHEEL
anytls_py-0.1.14.dist-info/entry_points.txt
anytls_py-0.1.14.dist-info/licenses/LICENSE
anytls_py-0.1.14.dist-info/RECORD
