Metadata-Version: 2.4
Name: anytls-py
Version: 0.1.14
Summary: mihomo-anytls-inbound manager
Author-email: QIN2DIM <yaoqinse@gmail.com>
License-File: LICENSE
Requires-Python: >=3.10
Requires-Dist: pyyaml<7.0,>=6.0
Requires-Dist: typer<1.0.0,>=0.15.4
